safemove/__init__.py
safemove/cli.py
safemove_tool-1.0.0.dist-info/METADATA
safemove_tool-1.0.0.dist-info/WHEEL
safemove_tool-1.0.0.dist-info/entry_points.txt
safemove_tool-1.0.0.dist-info/top_level.txt
safemove_tool-1.0.0.dist-info/RECORD
